setup.py
zayats/__init__.py
zayats/cosumer.py
zayats/publisher.py
zayats/utils.py
zayats.egg-info/PKG-INFO
zayats.egg-info/SOURCES.txt
zayats.egg-info/dependency_links.txt
zayats.egg-info/requires.txt
zayats.egg-info/top_level.txt