Metadata-Version: 1.2
Name: zayats
Version: 0.3.1
Summary: RabbitMQ simple fault-tolerant client (pika wrapper)
Home-page: https://github.com/RusJr/zayats
Author: Rus Jr
Author-email: binderrrr@gmail.com
License: MIT
Keywords: pika rabbit rabbitmq
Platform: UNKNOWN
Requires-Python: >=3.5
